setup.py
lawrenceliu/__init__.py
lawrenceliu.egg-info/PKG-INFO
lawrenceliu.egg-info/SOURCES.txt
lawrenceliu.egg-info/dependency_links.txt
lawrenceliu.egg-info/entry_points.txt
lawrenceliu.egg-info/top_level.txt