Metadata-Version: 1.0
Name: lawrenceliu
Version: 0.0.1
Summary: lawrenceliu的pypi测试
Home-page: https://github.com/LawrenceLiu
Author: lawrence
Author-email: liuchu1.0@gmail.com
License: UNKNOWN
Platform: UNKNOWN
